sjtools/__init__.py
sjtools-0.0.3.dist-info/LICENSE
sjtools-0.0.3.dist-info/METADATA
sjtools-0.0.3.dist-info/WHEEL
sjtools-0.0.3.dist-info/top_level.txt
sjtools-0.0.3.dist-info/RECORD
