Metadata-Version: 2.1
Name: sjtools
Version: 0.0.3
Summary: My test package
Home-page: https://t.me/sijeydev
Author: DEV|SJ
Author-email: sijeydev@gmail.com
License: MIT
Requires-Python: >=3.8
License-File: LICENSE
Requires-Dist: requests>=2.25.1
